chainmanager/__init__.py
chainmanager/__main__.py
chainmanager/form/__init__.py
chainmanager/form/chain_form.py
chainmanager/form/form_utils.py
chainmanager/form/job_form.py
chainmanager/form/main_controller.py
chainmanager/form/main_menu.py
chainmanager/model/__init__.py
chainmanager/model/chain.py
chainmanager/model/job.py
chainmanager/model/manager.py
chainmanager/ui/__init__.py
chainmanager/ui/file_chooser.py
chainmanager/web/main.html
chainmanager/web/bootstrap/css/bootstrap-grid.css
chainmanager/web/bootstrap/css/bootstrap-grid.min.css
chainmanager/web/bootstrap/css/bootstrap-reboot.css
chainmanager/web/bootstrap/css/bootstrap-reboot.min.css
chainmanager/web/bootstrap/css/bootstrap.css
chainmanager/web/bootstrap/css/bootstrap.min.css
chainmanager/web/bootstrap/css/theme/bootstrap.css
chainmanager/web/bootstrap/css/theme/bootstrap.min.css
chainmanager/web/bootstrap/css/theme2/bootstrap.css
chainmanager/web/bootstrap/css/theme2/bootstrap.min.css
chainmanager/web/bootstrap/js/bootstrap.bundle.js
chainmanager/web/bootstrap/js/bootstrap.bundle.min.js
chainmanager/web/bootstrap/js/bootstrap.js
chainmanager/web/bootstrap/js/bootstrap.min.js
chainmanager/web/js/controller.js
chainmanager/web/js/expose.js
chainmanager/web/js/jquery-3.4.1.min.js
chainmanager/web/js/login.js
chainmanager/web/js/prototype.js
chainmanager/web/js/sha256.js
chainmanager/web/swal/css/sweetalert2.css
chainmanager/web/swal/css/sweetalert2.min.css
chainmanager/web/swal/js/sweetalert2.all.js
chainmanager/web/swal/js/sweetalert2.all.min.js
chainmanager/web/swal/js/sweetalert2.js
chainmanager/web/swal/js/sweetalert2.min.js
chainmanager-0.1.2.dist-info/LICENSE
chainmanager-0.1.2.dist-info/METADATA
chainmanager-0.1.2.dist-info/WHEEL
chainmanager-0.1.2.dist-info/entry_points.txt
chainmanager-0.1.2.dist-info/top_level.txt
chainmanager-0.1.2.dist-info/RECORD
